lnkfile/__init__.py
lnkfile-0.2.1.dist-info/DESCRIPTION.rst
lnkfile-0.2.1.dist-info/METADATA
lnkfile-0.2.1.dist-info/RECORD
lnkfile-0.2.1.dist-info/WHEEL
lnkfile-0.2.1.dist-info/metadata.json
lnkfile-0.2.1.dist-info/top_level.txt
