Metadata-Version: 2.0
Name: lnkfile
Version: 0.2.1
Summary: Windows Shortcut file (LNK) parser
Home-page: https://github.com/silascutler/LnkParse
Author: Silas Cutler
Author-email: silas.cutler@gmail.com
License: MIT
Platform: UNKNOWN
